{
  "success": true,
  "count": 20,
  "certificates": [
    {
      "isin": "NLBNPIT292P6",
      "name": "BPA F LEV LG X 5 STELLANTIS IT 271235",
      "issuer": "BNP PARIBAS ISSUANCE B.V.",
      "type": "",
      "underlying_text": "Sottostante",
      "barrier_down": null,
      "maturity_date": "35-12-27",
      "annual_coupon_yield": null,
      "reference_price": 0.0002,
      "url": "https://www.borsaitaliana.it/borsa/cw-e-certificates/scheda/NLBNPIT292P6.html",
      "scraped_at": "2026-02-11T15:52:56.807104"
    },
    {
      "isin": "DE000VH2TMA6",
      "name": "VON TB SH ENI 18.15 B 18.15 OP END",
      "issuer": "VONTOBEL FINANCIAL PRODUCTS GMBH",
      "type": "",
      "underlying_text": "Sottostante",
      "barrier_down": null,
      "maturity_date": "N.D.",
      "annual_coupon_yield": null,
      "reference_price": 0.406,
      "url": "https://www.borsaitaliana.it/borsa/cw-e-certificates/scheda/DE000VH2TMA6.html",
      "scraped_at": "2026-02-11T15:53:28.594805"
    },
    {
      "isin": "DE000VJ1AWX7",
      "name": "VON EXP BMPS/BPER/CBK/DB/SG 60 150327",
      "issuer": "VONTOBEL FINANCIAL PRODUCTS GMBH",
      "type": "",
      "underlying_text": "Sottostante",
      "barrier_down": 60.0,
      "maturity_date": "27-03-15",
      "annual_coupon_yield": null,
      "reference_price": 101.3,
      "url": "https://www.borsaitaliana.it/borsa/cw-e-certificates/scheda/DE000VJ1AWX7.html",
      "scraped_at": "2026-02-11T15:53:35.177310"
    },
    {
      "isin": "NLBNPIT2UHL9",
      "name": "BPA CW PUT FinecoBank Banca 15 E 240326",
      "issuer": "BNP PARIBAS ISSUANCE B.V.",
      "type": "",
      "underlying_text": "Sottostante",
      "barrier_down": null,
      "maturity_date": "26-03-24",
      "annual_coupon_yield": null,
      "reference_price": 0.0014,
      "url": "https://www.borsaitaliana.it/borsa/cw-e-certificates/scheda/NLBNPIT2UHL9.html",
      "scraped_at": "2026-02-11T15:53:41.762900"
    },
    {
      "isin": "DE000UG453X2",
      "name": "UCH CW CALL FERRARI IT 480 A 180626",
      "issuer": "Unicredit Bank GmbH",
      "type": "",
      "underlying_text": "Sottostante",
      "barrier_down": null,
      "maturity_date": "26-06-18",
      "annual_coupon_yield": null,
      "reference_price": 0.04,
      "url": "https://www.borsaitaliana.it/borsa/cw-e-certificates/scheda/DE000UG453X2.html",
      "scraped_at": "2026-02-11T15:53:48.633410"
    },
    {
      "isin": "NLBNPIT2XUZ6",
      "name": "BPA TB LG FinecoBan 19.70 B 19.70 OP END",
      "issuer": "BNP PARIBAS ISSUANCE B.V.",
      "type": "",
      "underlying_text": "Sottostante",
      "barrier_down": null,
      "maturity_date": "N.D.",
      "annual_coupon_yield": null,
      "reference_price": 3.39,
      "url": "https://www.borsaitaliana.it/borsa/cw-e-certificates/scheda/NLBNPIT2XUZ6.html",
      "scraped_at": "2026-02-11T15:54:19.858016"
    },
    {
      "isin": "DE000VH5AKF2",
      "name": "VON F LEV LG X 4 Hims Hers Health 151228",
      "issuer": "VONTOBEL FINANCIAL PRODUCTS GMBH",
      "type": "",
      "underlying_text": "Sottostante",
      "barrier_down": null,
      "maturity_date": "28-12-15",
      "annual_coupon_yield": null,
      "reference_price": 0.0018,
      "url": "https://www.borsaitaliana.it/borsa/cw-e-certificates/scheda/DE000VH5AKF2.html",
      "scraped_at": "2026-02-11T15:54:26.475017"
    },
    {
      "isin": "NLBNPIT33SZ3",
      "name": "BPA TB LG Moderna I 36.93 B 36.93 OP END",
      "issuer": "BNP PARIBAS ISSUANCE B.V.",
      "type": "",
      "underlying_text": "Sottostante",
      "barrier_down": null,
      "maturity_date": "N.D.",
      "annual_coupon_yield": null,
      "reference_price": 0.612,
      "url": "https://www.borsaitaliana.it/borsa/cw-e-certificates/scheda/NLBNPIT33SZ3.html",
      "scraped_at": "2026-02-11T15:54:33.136625"
    },
    {
      "isin": "LU2141869003",
      "name": "SGE F LEV LG X 7 FTSE MIB NET TOT OP END",
      "issuer": "SOCIETE GENERALE EFFEKTEN GMBH",
      "type": "",
      "underlying_text": "Sottostante",
      "barrier_down": null,
      "maturity_date": "N.D.",
      "annual_coupon_yield": null,
      "reference_price": 14.9,
      "url": "https://www.borsaitaliana.it/borsa/cw-e-certificates/scheda/LU2141869003.html",
      "scraped_at": "2026-02-11T15:54:39.222205"
    },
    {
      "isin": "LU2141148952",
      "name": "SGE F LEV LG X 7 FTSE MIB NET TOT OP END",
      "issuer": "SOCIETE GENERALE EFFEKTEN GMBH",
      "type": "",
      "underlying_text": "Sottostante",
      "barrier_down": null,
      "maturity_date": "N.D.",
      "annual_coupon_yield": null,
      "reference_price": 115.35,
      "url": "https://www.borsaitaliana.it/borsa/cw-e-certificates/scheda/LU2141148952.html",
      "scraped_at": "2026-02-11T15:54:46.339698"
    },
    {
      "isin": "DE000SX1Y9K9",
      "name": "SGE F LEV SH X -7 FTSE MIB GROSS OP END",
      "issuer": "SOCIETE GENERALE EFFEKTEN GMBH",
      "type": "",
      "underlying_text": "Sottostante",
      "barrier_down": null,
      "maturity_date": "N.D.",
      "annual_coupon_yield": null,
      "reference_price": 0.705,
      "url": "https://www.borsaitaliana.it/borsa/cw-e-certificates/scheda/DE000SX1Y9K9.html",
      "scraped_at": "2026-02-11T15:55:18.061072"
    },
    {
      "isin": "DE000SF2GCY1",
      "name": "SGE F LEV LG X 5 Intesa Sanpaolo OP END",
      "issuer": "SOCIETE GENERALE EFFEKTEN GMBH",
      "type": "",
      "underlying_text": "Sottostante",
      "barrier_down": null,
      "maturity_date": "N.D.",
      "annual_coupon_yield": null,
      "reference_price": 132.4,
      "url": "https://www.borsaitaliana.it/borsa/cw-e-certificates/scheda/DE000SF2GCY1.html",
      "scraped_at": "2026-02-11T15:55:24.809526"
    },
    {
      "isin": "DE000VU33B74",
      "name": "VON F LEV LG X 3 Vont 3X L STLA 180627",
      "issuer": "VONTOBEL FINANCIAL PRODUCTS GMBH",
      "type": "",
      "underlying_text": "Sottostante",
      "barrier_down": null,
      "maturity_date": "27-06-18",
      "annual_coupon_yield": null,
      "reference_price": 0.0185,
      "url": "https://www.borsaitaliana.it/borsa/cw-e-certificates/scheda/DE000VU33B74.html",
      "scraped_at": "2026-02-11T15:55:31.508524"
    },
    {
      "isin": "DE000VD5TVQ0",
      "name": "VON F LEV SH X -5 Vont 5X S MODER 180627",
      "issuer": "VONTOBEL FINANCIAL PRODUCTS GMBH",
      "type": "",
      "underlying_text": "Sottostante",
      "barrier_down": null,
      "maturity_date": "27-06-18",
      "annual_coupon_yield": null,
      "reference_price": 0.0001,
      "url": "https://www.borsaitaliana.it/borsa/cw-e-certificates/scheda/DE000VD5TVQ0.html",
      "scraped_at": "2026-02-11T15:55:38.193009"
    },
    {
      "isin": "DE000SX1B024",
      "name": "SGE F LEV SH X -5 SPOTIFY TECHNOL OP END",
      "issuer": "SOCIETE GENERALE EFFEKTEN GMBH",
      "type": "",
      "underlying_text": "Sottostante",
      "barrier_down": null,
      "maturity_date": "N.D.",
      "annual_coupon_yield": null,
      "reference_price": 1.446,
      "url": "https://www.borsaitaliana.it/borsa/cw-e-certificates/scheda/DE000SX1B024.html",
      "scraped_at": "2026-02-11T15:55:44.918435"
    },
    {
      "isin": "DE000FD6GB45",
      "name": "SGE TB LG FinecoBan 20.12 B 20.12 OP END",
      "issuer": "SOCIETE GENERALE EFFEKTEN GMBH",
      "type": "",
      "underlying_text": "Sottostante",
      "barrier_down": null,
      "maturity_date": "N.D.",
      "annual_coupon_yield": null,
      "reference_price": 2.165,
      "url": "https://www.borsaitaliana.it/borsa/cw-e-certificates/scheda/DE000FD6GB45.html",
      "scraped_at": "2026-02-11T15:55:51.987715"
    },
    {
      "isin": "DE000FD6QDE8",
      "name": "SGE TB LG FinecoBan 19.61 B 19.61 OP END",
      "issuer": "SOCIETE GENERALE EFFEKTEN GMBH",
      "type": "",
      "underlying_text": "Sottostante",
      "barrier_down": null,
      "maturity_date": "N.D.",
      "annual_coupon_yield": null,
      "reference_price": 2.66,
      "url": "https://www.borsaitaliana.it/borsa/cw-e-certificates/scheda/DE000FD6QDE8.html",
      "scraped_at": "2026-02-11T15:56:00.277422"
    },
    {
      "isin": "DE000UG453Y0",
      "name": "UCH CW CALL FERRARI IT 500 A 180626",
      "issuer": "Unicredit Bank GmbH",
      "type": "",
      "underlying_text": "Sottostante",
      "barrier_down": null,
      "maturity_date": "26-06-18",
      "annual_coupon_yield": null,
      "reference_price": 0.0255,
      "url": "https://www.borsaitaliana.it/borsa/cw-e-certificates/scheda/DE000UG453Y0.html",
      "scraped_at": "2026-02-11T15:56:12.193778"
    },
    {
      "isin": "DE000SJ1CJD7",
      "name": "SGE F LEV LG X 3 STELLANTIS IT 200929",
      "issuer": "SOCIETE GENERALE EFFEKTEN GMBH",
      "type": "",
      "underlying_text": "Sottostante",
      "barrier_down": null,
      "maturity_date": "29-09-20",
      "annual_coupon_yield": null,
      "reference_price": 0.553,
      "url": "https://www.borsaitaliana.it/borsa/cw-e-certificates/scheda/DE000SJ1CJD7.html",
      "scraped_at": "2026-02-11T15:56:18.836513"
    },
    {
      "isin": "DE000SW7AKE7",
      "name": "SGE F LEV SH X -5 ORANGE JUICE FC 180326",
      "issuer": "SOCIETE GENERALE EFFEKTEN GMBH",
      "type": "",
      "underlying_text": "Sottostante",
      "barrier_down": null,
      "maturity_date": "26-03-18",
      "annual_coupon_yield": null,
      "reference_price": 0.0002,
      "url": "https://www.borsaitaliana.it/borsa/cw-e-certificates/scheda/DE000SW7AKE7.html",
      "scraped_at": "2026-02-11T15:56:25.509068"
    }
  ],
  "metadata": {
    "timestamp": "2026-02-11T15:56:27.085214",
    "version": "20.0"
  }
}